apimeter/__init__.py
apimeter/__main__.py
apimeter/api.py
apimeter/builtin/__init__.py
apimeter/builtin/comparators.py
apimeter/builtin/functions.py
apimeter/cli.py
apimeter/client.py
apimeter/compat.py
apimeter/context.py
apimeter/exceptions.py
apimeter/ext/__init__.py
apimeter/ext/har2case/__init__.py
apimeter/ext/locusts/README.md
apimeter/ext/locusts/__init__.py
apimeter/ext/locusts/__main__.py
apimeter/ext/locusts/cli.py
apimeter/ext/locusts/locustfile_template.py
apimeter/ext/locusts/utils.py
apimeter/ext/uploader/__init__.py
apimeter/loader/__init__.py
apimeter/loader/buildup.py
apimeter/loader/check.py
apimeter/loader/load.py
apimeter/loader/locate.py
apimeter/loader/schemas/api.schema.json
apimeter/loader/schemas/common.schema.json
apimeter/loader/schemas/testcase.schema.v1.json
apimeter/loader/schemas/testcase.schema.v2.json
apimeter/loader/schemas/testsuite.schema.v1.json
apimeter/loader/schemas/testsuite.schema.v2.json
apimeter/logger.py
apimeter/parser.py
apimeter/report/__init__.py
apimeter/report/html/__init__.py
apimeter/report/html/gen_report.py
apimeter/report/html/result.py
apimeter/report/html/template.html
apimeter/report/report.py
apimeter/report/stringify.py
apimeter/report/summarize.py
apimeter/response.py
apimeter/runner.py
apimeter/utils.py
apimeter/validator.py
apimeter-2.85.dist-info/LICENSE
apimeter-2.85.dist-info/METADATA
apimeter-2.85.dist-info/WHEEL
apimeter-2.85.dist-info/entry_points.txt
apimeter-2.85.dist-info/RECORD
