Metadata-Version: 2.3
Name: apimeter
Version: 2.85
Summary: One-stop solution for HTTP(S) testing.
License: Apache-2.0
Keywords: HTTP,api,test,requests,locustio
Author: debugtalk
Author-email: debugtalk@gmail.com
Requires-Python: >=3.6,<4.0
Classifier: Development Status :: 5 - Production/Stable
Classifier: License :: OSI Approved :: Apache Software License
Classifier: Operating System :: MacOS
Classifier: Operating System :: Microsoft :: Windows
Classifier: Operating System :: POSIX :: Linux
Classifier: Programming Language :: Python :: 3
Classifier: Programming Language :: Python :: 3.6
Classifier: Programming Language :: Python :: 3.7
Classifier: Programming Language :: Python :: 3.8
Classifier: Programming Language :: Python :: 3.9
Classifier: Programming Language :: Python :: 3.10
Classifier: Programming Language :: Python :: 3.11
Classifier: Programming Language :: Python :: 3.12
Classifier: Programming Language :: Python :: 3.13
Classifier: Topic :: Software Development :: Libraries :: Python Modules
Classifier: Topic :: Software Development :: Quality Assurance
Classifier: Topic :: Software Development :: Testing
Requires-Dist: colorama (==0.4.1)
Requires-Dist: colorlog (==4.0.2)
Requires-Dist: filetype (==1.0.5)
Requires-Dist: har2case (==0.3.1)
Requires-Dist: jinja2 (==2.10.3)
Requires-Dist: jsonpath (==0.82.2)
Requires-Dist: jsonschema (==3.2.0)
Requires-Dist: markupsafe (==1.1.1)
Requires-Dist: pyyaml (==5.1.2)
Requires-Dist: requests (>=2.22.0,<3.0.0)
Requires-Dist: requests-toolbelt (>=0.9.1,<0.10.0)
Requires-Dist: sentry-sdk (==0.13.5)
Project-URL: Documentation, https://docs.httprunner.org
Project-URL: Homepage, https://github.com/httprunner/httprunner
Project-URL: Repository, https://github.com/httprunner/httprunner
